multicast.py
multicast_py-1.0.0.dist-info/LICENSE
multicast_py-1.0.0.dist-info/WHEEL
multicast_py-1.0.0.dist-info/METADATA
multicast_py-1.0.0.dist-info/RECORD
