Metadata-Version: 2.1
Name: multicast-py
Version: 1.0.0
Summary: Low-to-mid level wrapper for multicast sockets
Keywords: 
Author-email: Pavel Dunaev <me@neko-dev.ru>
Requires-Python: >= 3.10
Classifier: License :: OSI Approved :: MIT License
Classifier: Operating System :: Microsoft :: Windows
Classifier: Operating System :: POSIX :: Linux
Classifier: Programming Language :: Python
Classifier: Typing :: Typed
Project-URL: Home, https://gitlab.neko-dev.ru/me/multicast-py
Project-URL: Issues, https://gitlab.neko-dev.ru/me/multicast-py/-/issues
Project-URL: Repository, https://gitlab.neko-dev.ru/me/multicast-py
